params/__init__.py
params/compat.py
params/core.py
params/fields.py
params/utils.py
params/contrib/__init__.py
params/contrib/base.py
params/contrib/django.py
params/contrib/tornado.py
params-0.8.1.dist-info/METADATA
params-0.8.1.dist-info/WHEEL
params-0.8.1.dist-info/top_level.txt
params-0.8.1.dist-info/RECORD
