Metadata-Version: 2.1
Name: params
Version: 0.8.1
Summary: General purpose parameter validator for web development
Home-page: https://github.com/reorx/params
Author: reorx
Author-email: novoreorx@gmail.com
License: UNKNOWN
Platform: UNKNOWN
Requires-Dist: six
